LoggingDecorator/LoggingDecorator.py
LoggingDecorator/__init__.py
logging_decorator-1.0.1.dist-info/LICENSE
logging_decorator-1.0.1.dist-info/METADATA
logging_decorator-1.0.1.dist-info/WHEEL
logging_decorator-1.0.1.dist-info/top_level.txt
logging_decorator-1.0.1.dist-info/RECORD
