Metadata-Version: 2.1
Name: logging-decorator
Version: 1.0.1
Summary: A simple method decorator to generate logs easily.
Home-page: https://github.com/lkellermann/logging-decorator
Author: Leandro Kellermann de Oliveira
Author-email: kellermann@alumni.usp.br
License: UNKNOWN
Project-URL: Status, https://github.com/lkellermann/logging-decorator/blob/main
Project-URL: Pull requests, https://github.com/lkellermann/logging-decorator/pulls
Project-URL: Issues, https://github.com/lkellermann/logging-decorator/issues
Project-URL: License, https://github.com/lkellermann/logging-decorator/blob/main/license
Platform: UNKNOWN
Classifier: Programming Language :: Python :: 3
Classifier: License :: OSI Approved :: MIT License
Classifier: Operating System :: OS Independent
Requires-Python: >=3.6
License-File: LICENSE
